[{"courses":["Accounting"],"email":"Terry.Alvarez@gmail.com"},{"courses":["Sculpture"],"email":"Lawrence.Bailey@gmail.com"},{"courses":["Accounting"],"email":"Madison.Gray@gmail.com"},{"courses":["History"],"email":"Shirley.Hall@gmail.com"},{"courses":["Drawing"],"email":"Roy.Martinez@gmail.com"},{"courses":["Literature and Poetry"],"email":"Betty.Ortiz@gmail.com"},{"courses":["English"],"email":"Janice.Ortiz@gmail.com"},{"courses":["Sculpture"],"email":"Kelly.Rogers@gmail.com"},{"courses":["Law"],"email":"Sophia.Sanchez@gmail.com"},{"courses":["Law"],"email":"Janice.Watson@gmail.com"}]