[{"courses":["History"],"email":"Adam.Adams@gmail.com"},{"courses":["Sculpture"],"email":"Catherine.Adams@gmail.com"},{"courses":["Sculpture"],"email":"Jesse.Adams@gmail.com"},{"courses":["Law"],"email":"Gerald.Allen@gmail.com"},{"courses":["Literature and Poetry"],"email":"Gloria.Allen@gmail.com"},{"courses":["Literature and Poetry"],"email":"Marie.Allen@gmail.com"},{"courses":["Accounting"],"email":"Logan.Alvarez@gmail.com"},{"courses":["Chemistry"],"email":"Matthew.Alvarez@gmail.com"},{"courses":["Literature and Poetry"],"email":"Rachel.Alvarez@gmail.com"},{"courses":["Chemistry"],"email":"Russell.Alvarez@gmail.com"},{"courses":["Drawing"],"email":"Christina.Anderson@gmail.com"},{"courses":["Chemistry"],"email":"Kimberly.Anderson@gmail.com"},{"courses":["English"],"email":"Michael.Anderson@gmail.com"},{"courses":["Chemistry"],"email":"Ruth.Anderson@gmail.com"},{"courses":["Accounting"],"email":"Sophia.Anderson@gmail.com"},{"courses":["Chemistry"],"email":"Benjamin.Bailey@gmail.com"},{"courses":["History"],"email":"Brenda.Bailey@gmail.com"},{"courses":["Sculpture"],"email":"Michelle.Bailey@gmail.com"},{"courses":["Sculpture"],"email":"Sean.Baker@gmail.com"},{"courses":["History"],"email":"Gregory.Bennet@gmail.com"},{"courses":["Physics"],"email":"Rebecca.Bennet@gmail.com"},{"courses":["Drawing"],"email":"Roy.Bennet@gmail.com"},{"courses":["History"],"email":"Barbara.Brooks@gmail.com"},{"courses":["Latin"],"email":"Melissa.Brooks@gmail.com"},{"courses":["Literature and Poetry"],"email":"Peter.Brooks@gmail.com"},{"courses":["Sculpture"],"email":"Stephanie.Brooks@gmail.com"},{"courses":["History"],"email":"Stephen.Brooks@gmail.com"},{"courses":["Drawing"],"email":"Catherine.Brown@gmail.com"},{"courses":["English"],"email":"Kelly.Brown@gmail.com"},{"courses":["Mathematics"],"email":"Lawrence.Brown@gmail.com"},{"courses":["Physics"],"email":"Michelle.Brown@gmail.com"},{"courses":["Literature and Poetry"],"email":"Natalie.Brown@gmail.com"},{"courses":["Physics"],"email":"Roy.Brown@gmail.com"},{"courses":["Latin"],"email":"Albert.Campbell@gmail.com"},{"courses":["Physics"],"email":"Bobby.Campbell@gmail.com"},{"courses":["Accounting"],"email":"Gabriel.Campbell@gmail.com"},{"courses":["Accounting"],"email":"Gloria.Campbell@gmail.com"},{"courses":["Physics"],"email":"Henry.Campbell@gmail.com"},{"courses":["Latin"],"email":"Joe.Campbell@gmail.com"},{"courses":["History"],"email":"Rose.Campbell@gmail.com"},{"courses":["Law"],"email":"Andrea.Carter@gmail.com"},{"courses":["Law"],"email":"Martha.Carter@gmail.com"},{"courses":["Chemistry"],"email":"Nicholas.Carter@gmail.com"},{"courses":["History"],"email":"Tyler.Carter@gmail.com"},{"courses":["Latin"],"email":"Victoria.Carter@gmail.com"},{"courses":["Chemistry"],"email":"Billy.Castillo@gmail.com"},{"courses":["Sculpture"],"email":"Brenda.Castillo@gmail.com"},{"courses":["Literature and Poetry"],"email":"Donna.Castillo@gmail.com"},{"courses":["Chemistry"],"email":"Dorothy.Castillo@gmail.com"},{"courses":["Accounting"],"email":"Kathleen.Castillo@gmail.com"},{"courses":["Sculpture"],"email":"Maria.Castillo@gmail.com"},{"courses":["Physics"],"email":"Natalie.Castillo@gmail.com"},{"courses":["Latin"],"email":"Sarah.Castillo@gmail.com"},{"courses":["Law"],"email":"Sharon.Castillo@gmail.com"},{"courses":["Literature and Poetry"],"email":"Katherine.Chavez@gmail.com"},{"courses":["Literature and Poetry"],"email":"Marilyn.Chavez@gmail.com"},{"courses":["Drawing"],"email":"Abigail.Clark@gmail.com"},{"courses":["Law"],"email":"Heather.Clark@gmail.com"},{"courses":["Management"],"email":"Jordan.Clark@gmail.com"},{"courses":["Law"],"email":"Juan.Clark@gmail.com"},{"courses":["Literature and Poetry"],"email":"Julie.Clark@gmail.com"},{"courses":["Accounting"],"email":"Ryan.Clark@gmail.com"},{"courses":["Latin"],"email":"Steven.Clark@gmail.com"},{"courses":["Management"],"email":"Susan.Clark@gmail.com"},{"courses":["Mathematics"],"email":"Betty.Collins@gmail.com"},{"courses":["Physics"],"email":"Dylan.Collins@gmail.com"},{"courses":["Biology"],"email":"Kathleen.Collins@gmail.com"},{"courses":["Drawing"],"email":"Kathryn.Collins@gmail.com"},{"courses":["Law"],"email":"Alice.Cook@gmail.com"},{"courses":["Biology"],"email":"Barbara.Cook@gmail.com"},{"courses":["Physics"],"email":"Jonathan.Cook@gmail.com"},{"courses":["History"],"email":"Julia.Cook@gmail.com"},{"courses":["Sculpture"],"email":"Laura.Cook@gmail.com"},{"courses":["Literature and Poetry"],"email":"Sophia.Cook@gmail.com"},{"courses":["Accounting"],"email":"Teresa.Cook@gmail.com"},{"courses":["Accounting"],"email":"Carol.Cooper@gmail.com"},{"courses":["Latin"],"email":"Charles.Cooper@gmail.com"},{"courses":["Latin"],"email":"Daniel.Cooper@gmail.com"},{"courses":["Accounting"],"email":"Diana.Cooper@gmail.com"},{"courses":["Chemistry"],"email":"Martha.Cooper@gmail.com"},{"courses":["Accounting"],"email":"Roy.Cooper@gmail.com"},{"courses":["Biology"],"email":"Emma.Cox@gmail.com"},{"courses":["Chemistry"],"email":"Sophia.Cox@gmail.com"},{"courses":["Management","Management"],"email":"Lauren.Cruz@gmail.com"},{"courses":["Mathematics"],"email":"Pamela.Cruz@gmail.com"},{"courses":["Biology"],"email":"Stephanie.Cruz@gmail.com"},{"courses":["Law"],"email":"Bobby.Davis@gmail.com"},{"courses":["Chemistry"],"email":"Dennis.Davis@gmail.com"},{"courses":["English"],"email":"Frank.Davis@gmail.com"},{"courses":["Management"],"email":"Louis.Davis@gmail.com"},{"courses":["Accounting"],"email":"Samantha.Davis@gmail.com"},{"courses":["English"],"email":"Susan.Davis@gmail.com"},{"courses":["English"],"email":"Brandon.Diaz@gmail.com"},{"courses":["Chemistry"],"email":"Martha.Diaz@gmail.com"},{"courses":["Law"],"email":"Peter.Diaz@gmail.com"},{"courses":["Drawing"],"email":"Sandra.Diaz@gmail.com"},{"courses":["History"],"email":"Theresa.Diaz@gmail.com"},{"courses":["Literature and Poetry"],"email":"Bobby.Edwards@gmail.com"},{"courses":["Biology"],"email":"Brian.Edwards@gmail.com"},{"courses":["Management"],"email":"Janice.Edwards@gmail.com"},{"courses":["Sculpture"],"email":"Tyler.Edwards@gmail.com"},{"courses":["Accounting"],"email":"Beverly.Evans@gmail.com"},{"courses":["Accounting"],"email":"Cynthia.Evans@gmail.com"},{"courses":["Accounting"],"email":"Eric.Evans@gmail.com"},{"courses":["Sculpture"],"email":"Nathan.Evans@gmail.com"},{"courses":["Management"],"email":"Christina.Flores@gmail.com"},{"courses":["English"],"email":"Deborah.Flores@gmail.com"},{"courses":["Mathematics"],"email":"Frances.Flores@gmail.com"},{"courses":["Sculpture"],"email":"Jean.Flores@gmail.com"},{"courses":["Sculpture"],"email":"Maria.Flores@gmail.com"},{"courses":["Drawing"],"email":"Raymond.Flores@gmail.com"},{"courses":["Physics"],"email":"Zachary.Flores@gmail.com"},{"courses":["History"],"email":"Anthony.Foster@gmail.com"},{"courses":["Accounting"],"email":"Carolyn.Foster@gmail.com"},{"courses":["Mathematics"],"email":"Denise.Foster@gmail.com"},{"courses":["Law"],"email":"Isabella.Foster@gmail.com"},{"courses":["English"],"email":"James.Foster@gmail.com"},{"courses":["Biology"],"email":"Logan.Foster@gmail.com"},{"courses":["Sculpture"],"email":"Martha.Foster@gmail.com"},{"courses":["Law"],"email":"Pamela.Foster@gmail.com"},{"courses":["Drawing"],"email":"Raymond.Foster@gmail.com"},{"courses":["Mathematics"],"email":"Carolyn.Garcia@gmail.com"},{"courses":["Sculpture"],"email":"Christine.Garcia@gmail.com"},{"courses":["Law"],"email":"Edward.Garcia@gmail.com"},{"courses":["Literature and Poetry"],"email":"Frank.Garcia@gmail.com"},{"courses":["Literature and Poetry"],"email":"Marie.Garcia@gmail.com"},{"courses":["Drawing"],"email":"Philip.Garcia@gmail.com"},{"courses":["Management"],"email":"Sarah.Garcia@gmail.com"},{"courses":["Drawing"],"email":"Steven.Garcia@gmail.com"},{"courses":["Accounting"],"email":"Abigail.Gomez@gmail.com"},{"courses":["History"],"email":"Beverly.Gomez@gmail.com"},{"courses":["Chemistry"],"email":"Debra.Gomez@gmail.com"},{"courses":["Literature and Poetry"],"email":"Mark.Gomez@gmail.com"},{"courses":["Biology"],"email":"Brian.Gonzales@gmail.com"},{"courses":["Physics"],"email":"Charlotte.Gonzales@gmail.com"},{"courses":["Law"],"email":"Frank.Gonzales@gmail.com"},{"courses":["Management"],"email":"Jeremy.Gonzales@gmail.com"},{"courses":["English"],"email":"Sharon.Gonzales@gmail.com"},{"courses":["Latin"],"email":"Alexander.Gray@gmail.com"},{"courses":["History"],"email":"Donna.Gray@gmail.com"},{"courses":["History"],"email":"Gregory.Gray@gmail.com"},{"courses":["Mathematics"],"email":"Joyce.Gray@gmail.com"},{"courses":["Accounting"],"email":"Andrea.Green@gmail.com"},{"courses":["Physics"],"email":"Isabella.Green@gmail.com"},{"courses":["Biology"],"email":"Jack.Green@gmail.com"},{"courses":["Latin"],"email":"Steven.Green@gmail.com"},{"courses":["Law"],"email":"Benjamin.Gutierrez@gmail.com"},{"courses":["Drawing"],"email":"Brian.Gutierrez@gmail.com"},{"courses":["Biology"],"email":"Christopher.Gutierrez@gmail.com"},{"courses":["Mathematics"],"email":"Sandra.Gutierrez@gmail.com"},{"courses":["Physics"],"email":"Benjamin.Hall@gmail.com"},{"courses":["Management"],"email":"Donald.Hall@gmail.com"},{"courses":["Law"],"email":"Jason.Hall@gmail.com"},{"courses":["Management"],"email":"Karen.Hall@gmail.com"},{"courses":["Sculpture"],"email":"Lauren.Hall@gmail.com"},{"courses":["Management"],"email":"Louis.Hall@gmail.com"},{"courses":["Latin"],"email":"Stephen.Hall@gmail.com"},{"courses":["Accounting"],"email":"Frank.Harris@gmail.com"},{"courses":["Drawing"],"email":"Judy.Harris@gmail.com"},{"courses":["Accounting"],"email":"Marie.Harris@gmail.com"},{"courses":["Drawing"],"email":"Marilyn.Harris@gmail.com"},{"courses":["Physics"],"email":"Scott.Harris@gmail.com"},{"courses":["Law"],"email":"Aaron.Hernandez@gmail.com"},{"courses":["English"],"email":"Edward.Hernandez@gmail.com"},{"courses":["Mathematics"],"email":"Katherine.Hernandez@gmail.com"},{"courses":["Mathematics"],"email":"Marilyn.Hernandez@gmail.com"},{"courses":["Chemistry"],"email":"Anna.Hill@gmail.com"},{"courses":["Physics"],"email":"Carol.Hill@gmail.com"},{"courses":["Accounting"],"email":"Eric.Hill@gmail.com"},{"courses":["Management"],"email":"Frank.Hill@gmail.com"},{"courses":["Literature and Poetry"],"email":"Kevin.Hill@gmail.com"},{"courses":["Latin"],"email":"Sharon.Hill@gmail.com"},{"courses":["Latin"],"email":"Daniel.Howard@gmail.com"},{"courses":["Biology"],"email":"Rachel.Howard@gmail.com"},{"courses":["English"],"email":"Ronald.Howard@gmail.com"},{"courses":["Mathematics"],"email":"Christina.Hughes@gmail.com"},{"courses":["English"],"email":"Matthew.Hughes@gmail.com"},{"courses":["History"],"email":"Tyler.Hughes@gmail.com"},{"courses":["Literature and Poetry"],"email":"Brian.Jackson@gmail.com"},{"courses":["Latin"],"email":"Frank.Jackson@gmail.com"},{"courses":["Law"],"email":"Harold.Jackson@gmail.com"},{"courses":["Accounting"],"email":"Jack.Jackson@gmail.com"},{"courses":["Latin"],"email":"Doris.James@gmail.com"},{"courses":["Sculpture","Literature and Poetry"],"email":"Gary.James@gmail.com"},{"courses":["Law"],"email":"Maria.James@gmail.com"},{"courses":["Sculpture"],"email":"Martha.James@gmail.com"},{"courses":["Literature and Poetry"],"email":"Patrick.James@gmail.com"},{"courses":["Biology"],"email":"Rose.James@gmail.com"},{"courses":["Latin"],"email":"Sophia.James@gmail.com"},{"courses":["Law"],"email":"Timothy.James@gmail.com"},{"courses":["Physics"],"email":"Albert.Jimenez@gmail.com"},{"courses":["Management"],"email":"Edward.Jimenez@gmail.com"},{"courses":["Management"],"email":"Harold.Jimenez@gmail.com"},{"courses":["Biology"],"email":"Janice.Jimenez@gmail.com"},{"courses":["Law"],"email":"Thomas.Jimenez@gmail.com"},{"courses":["Literature and Poetry"],"email":"Timothy.Jimenez@gmail.com"},{"courses":["English"],"email":"Doris.Johnson@gmail.com"},{"courses":["Chemistry"],"email":"Judith.Johnson@gmail.com"},{"courses":["Mathematics"],"email":"Richard.Johnson@gmail.com"},{"courses":["Physics"],"email":"Willie.Johnson@gmail.com"},{"courses":["Literature and Poetry"],"email":"Aaron.Jones@gmail.com"},{"courses":["History"],"email":"Elizabeth.Jones@gmail.com"},{"courses":["English"],"email":"Katherine.Jones@gmail.com"},{"courses":["English"],"email":"Roy.Jones@gmail.com"},{"courses":["Chemistry"],"email":"Ryan.Jones@gmail.com"},{"courses":["Accounting"],"email":"Deborah.Kelly@gmail.com"},{"courses":["Drawing"],"email":"Keith.Kelly@gmail.com"},{"courses":["Latin","Latin"],"email":"Laura.Kelly@gmail.com"},{"courses":["Literature and Poetry"],"email":"Rachel.Kelly@gmail.com"},{"courses":["Accounting"],"email":"Jeffrey.Kim@gmail.com"},{"courses":["Chemistry"],"email":"Joe.Kim@gmail.com"},{"courses":["Mathematics"],"email":"Amanda.King@gmail.com"},{"courses":["Mathematics"],"email":"Eric.King@gmail.com"},{"courses":["English"],"email":"Ethan.King@gmail.com"},{"courses":["Chemistry"],"email":"Johnny.King@gmail.com"},{"courses":["Management"],"email":"Kelly.King@gmail.com"},{"courses":["Latin"],"email":"Louis.King@gmail.com"},{"courses":["Management"],"email":"Rose.King@gmail.com"},{"courses":["Mathematics"],"email":"Adam.Lee@gmail.com"},{"courses":["Literature and Poetry"],"email":"Daniel.Lee@gmail.com"},{"courses":["Literature and Poetry"],"email":"Diane.Lee@gmail.com"},{"courses":["Physics"],"email":"Jesse.Lee@gmail.com"},{"courses":["Management"],"email":"Jordan.Lee@gmail.com"},{"courses":["Literature and Poetry"],"email":"Joyce.Lee@gmail.com"},{"courses":["Latin"],"email":"Amber.Lewis@gmail.com"},{"courses":["Sculpture"],"email":"Beverly.Lewis@gmail.com"},{"courses":["Literature and Poetry"],"email":"Jack.Lewis@gmail.com"},{"courses":["Law"],"email":"Jacqueline.Lewis@gmail.com"},{"courses":["Drawing"],"email":"Kathryn.Lewis@gmail.com"},{"courses":["Sculpture"],"email":"Olivia.Lewis@gmail.com"},{"courses":["Chemistry"],"email":"Bryan.Long@gmail.com"},{"courses":["English"],"email":"David.Long@gmail.com"},{"courses":["Law"],"email":"Emily.Long@gmail.com"},{"courses":["Sculpture"],"email":"Janet.Long@gmail.com"},{"courses":["Chemistry"],"email":"Nicholas.Long@gmail.com"},{"courses":["Literature and Poetry"],"email":"Christina.Lopez@gmail.com"},{"courses":["English"],"email":"Danielle.Lopez@gmail.com"},{"courses":["Literature and Poetry"],"email":"Gloria.Lopez@gmail.com"},{"courses":["Latin"],"email":"Jonathan.Lopez@gmail.com"},{"courses":["History"],"email":"Frances.Martin@gmail.com"},{"courses":["English"],"email":"Paul.Martin@gmail.com"},{"courses":["Accounting"],"email":"Teresa.Martin@gmail.com"},{"courses":["History"],"email":"Vincent.Martin@gmail.com"},{"courses":["Latin"],"email":"Abigail.Martinez@gmail.com"},{"courses":["Law"],"email":"Billy.Martinez@gmail.com"},{"courses":["History"],"email":"Charles.Martinez@gmail.com"},{"courses":["Mathematics"],"email":"Elizabeth.Martinez@gmail.com"},{"courses":["Latin"],"email":"Adam.Mendoza@gmail.com"},{"courses":["English"],"email":"Amber.Mendoza@gmail.com"},{"courses":["Law"],"email":"Charlotte.Mendoza@gmail.com"},{"courses":["Biology"],"email":"Kathryn.Mendoza@gmail.com"},{"courses":["English"],"email":"Ralph.Mendoza@gmail.com"},{"courses":["Chemistry"],"email":"Adam.Miller@gmail.com"},{"courses":["Law"],"email":"Charles.Miller@gmail.com"},{"courses":["Physics"],"email":"Grace.Miller@gmail.com"},{"courses":["Accounting"],"email":"Helen.Miller@gmail.com"},{"courses":["Law"],"email":"Joseph.Miller@gmail.com"},{"courses":["Drawing"],"email":"Kayla.Miller@gmail.com"},{"courses":["Sculpture"],"email":"Olivia.Miller@gmail.com"},{"courses":["Management"],"email":"Ralph.Miller@gmail.com"},{"courses":["English"],"email":"Billy.Mitchell@gmail.com"},{"courses":["Accounting"],"email":"Christine.Mitchell@gmail.com"},{"courses":["Physics"],"email":"Dennis.Mitchell@gmail.com"},{"courses":["English"],"email":"Diana.Mitchell@gmail.com"},{"courses":["Sculpture"],"email":"Isabella.Mitchell@gmail.com"},{"courses":["Latin"],"email":"William.Mitchell@gmail.com"},{"courses":["Latin"],"email":"Aaron.Moore@gmail.com"},{"courses":["Accounting"],"email":"Abigail.Moore@gmail.com"},{"courses":["Accounting"],"email":"Jacob.Moore@gmail.com"},{"courses":["Law"],"email":"Kenneth.Moore@gmail.com"},{"courses":["Mathematics"],"email":"Kimberly.Moore@gmail.com"},{"courses":["Drawing"],"email":"Martha.Moore@gmail.com"},{"courses":["Chemistry"],"email":"Terry.Moore@gmail.com"},{"courses":["Sculpture"],"email":"Debra.Morales@gmail.com"},{"courses":["English"],"email":"Jesse.Morales@gmail.com"},{"courses":["Chemistry"],"email":"Kenneth.Morgan@gmail.com"},{"courses":["Accounting"],"email":"Ryan.Morgan@gmail.com"},{"courses":["Management"],"email":"Shirley.Morgan@gmail.com"},{"courses":["Mathematics"],"email":"Eugene.Morris@gmail.com"},{"courses":["Law"],"email":"Zachary.Morris@gmail.com"},{"courses":["Law"],"email":"Adam.Murphy@gmail.com"},{"courses":["Accounting"],"email":"Austin.Murphy@gmail.com"},{"courses":["English"],"email":"David.Murphy@gmail.com"},{"courses":["Drawing"],"email":"Kayla.Murphy@gmail.com"},{"courses":["History"],"email":"Wayne.Murphy@gmail.com"},{"courses":["Latin"],"email":"Amanda.Nelson@gmail.com"},{"courses":["Law"],"email":"Dorothy.Nelson@gmail.com"},{"courses":["Mathematics"],"email":"Hannah.Nelson@gmail.com"},{"courses":["Latin"],"email":"Margaret.Nelson@gmail.com"},{"courses":["Literature and Poetry"],"email":"Douglas.Nguyen@gmail.com"},{"courses":["Latin"],"email":"Philip.Nguyen@gmail.com"},{"courses":["Biology"],"email":"Danielle.Ortiz@gmail.com"},{"courses":["Latin"],"email":"Henry.Ortiz@gmail.com"},{"courses":["Mathematics"],"email":"Janet.Ortiz@gmail.com"},{"courses":["Chemistry"],"email":"Jeremy.Ortiz@gmail.com"},{"courses":["Law"],"email":"Kathleen.Ortiz@gmail.com"},{"courses":["Literature and Poetry"],"email":"Keith.Ortiz@gmail.com"},{"courses":["History"],"email":"Mark.Ortiz@gmail.com"},{"courses":["Law"],"email":"Carolyn.Parker@gmail.com"},{"courses":["Drawing"],"email":"Marilyn.Parker@gmail.com"},{"courses":["Physics"],"email":"Megan.Parker@gmail.com"},{"courses":["Management"],"email":"Michelle.Parker@gmail.com"},{"courses":["Literature and Poetry"],"email":"Samantha.Parker@gmail.com"},{"courses":["Chemistry"],"email":"William.Parker@gmail.com"},{"courses":["Mathematics"],"email":"Billy.Patel@gmail.com"},{"courses":["Accounting"],"email":"Bryan.Patel@gmail.com"},{"courses":["Biology"],"email":"Dylan.Patel@gmail.com"},{"courses":["Law"],"email":"Jose.Patel@gmail.com"},{"courses":["Management"],"email":"Robert.Patel@gmail.com"},{"courses":["English"],"email":"Roy.Patel@gmail.com"},{"courses":["Sculpture"],"email":"Angela.Perez@gmail.com"},{"courses":["History"],"email":"Ethan.Perez@gmail.com"},{"courses":["Drawing"],"email":"Frances.Perez@gmail.com"},{"courses":["English"],"email":"Jason.Perez@gmail.com"},{"courses":["Management"],"email":"Jessica.Perez@gmail.com"},{"courses":["History"],"email":"Keith.Perez@gmail.com"},{"courses":["History"],"email":"Steven.Perez@gmail.com"},{"courses":["Mathematics"],"email":"Abigail.Peterson@gmail.com"},{"courses":["Physics"],"email":"Austin.Peterson@gmail.com"},{"courses":["Biology"],"email":"Betty.Peterson@gmail.com"},{"courses":["Sculpture"],"email":"Gerald.Peterson@gmail.com"},{"courses":["Literature and Poetry"],"email":"Justin.Peterson@gmail.com"},{"courses":["Biology"],"email":"Marilyn.Peterson@gmail.com"},{"courses":["Biology"],"email":"Dorothy.Phillips@gmail.com"},{"courses":["Management"],"email":"Gregory.Phillips@gmail.com"},{"courses":["Drawing"],"email":"Jeffrey.Phillips@gmail.com"},{"courses":["Chemistry"],"email":"Jerry.Phillips@gmail.com"},{"courses":["Physics"],"email":"Jessica.Phillips@gmail.com"},{"courses":["English"],"email":"Brian.Price@gmail.com"},{"courses":["English"],"email":"Charlotte.Price@gmail.com"},{"courses":["English"],"email":"Beverly.Ramirez@gmail.com"},{"courses":["Latin"],"email":"Charles.Ramirez@gmail.com"},{"courses":["Accounting"],"email":"Charlotte.Ramirez@gmail.com"},{"courses":["Physics"],"email":"Patricia.Ramirez@gmail.com"},{"courses":["Literature and Poetry"],"email":"Randy.Ramirez@gmail.com"},{"courses":["Management"],"email":"Sophia.Ramirez@gmail.com"},{"courses":["English"],"email":"Benjamin.Ramos@gmail.com"},{"courses":["Latin","Latin"],"email":"Gary.Ramos@gmail.com"},{"courses":["Management"],"email":"Larry.Ramos@gmail.com"},{"courses":["Accounting"],"email":"Olivia.Ramos@gmail.com"},{"courses":["Drawing"],"email":"Susan.Ramos@gmail.com"},{"courses":["English"],"email":"Arthur.Reed@gmail.com"},{"courses":["Literature and Poetry"],"email":"Brian.Reed@gmail.com"},{"courses":["Physics"],"email":"Brittany.Reed@gmail.com"},{"courses":["Chemistry"],"email":"Larry.Reed@gmail.com"},{"courses":["Physics"],"email":"Sandra.Reed@gmail.com"},{"courses":["Mathematics"],"email":"Adam.Reyes@gmail.com"},{"courses":["Physics"],"email":"Benjamin.Reyes@gmail.com"},{"courses":["Drawing"],"email":"Brandon.Reyes@gmail.com"},{"courses":["Drawing"],"email":"Victoria.Reyes@gmail.com"},{"courses":["Law"],"email":"Wayne.Reyes@gmail.com"},{"courses":["History"],"email":"Christine.Richardson@gmail.com"},{"courses":["Drawing"],"email":"Christopher.Richardson@gmail.com"},{"courses":["Chemistry"],"email":"Marie.Richardson@gmail.com"},{"courses":["Biology","Drawing"],"email":"Ralph.Richardson@gmail.com"},{"courses":["Latin"],"email":"Austin.Rivera@gmail.com"},{"courses":["Law"],"email":"Jordan.Rivera@gmail.com"},{"courses":["Law"],"email":"Kayla.Rivera@gmail.com"},{"courses":["History"],"email":"Matthew.Rivera@gmail.com"},{"courses":["Chemistry"],"email":"Natalie.Rivera@gmail.com"},{"courses":["Biology"],"email":"Rebecca.Rivera@gmail.com"},{"courses":["Drawing"],"email":"Maria.Roberts@gmail.com"},{"courses":["Law"],"email":"Martha.Roberts@gmail.com"},{"courses":["Latin"],"email":"Pamela.Roberts@gmail.com"},{"courses":["Sculpture"],"email":"Douglas.Robinson@gmail.com"},{"courses":["History"],"email":"Eugene.Robinson@gmail.com"},{"courses":["Biology"],"email":"Melissa.Robinson@gmail.com"},{"courses":["Law"],"email":"Rose.Robinson@gmail.com"},{"courses":["Management"],"email":"Sandra.Robinson@gmail.com"},{"courses":["Management"],"email":"Susan.Robinson@gmail.com"},{"courses":["Management"],"email":"Frank.Rodriguez@gmail.com"},{"courses":["Sculpture"],"email":"Joyce.Rodriguez@gmail.com"},{"courses":["Literature and Poetry"],"email":"Patricia.Rodriguez@gmail.com"},{"courses":["Management"],"email":"Carolyn.Rogers@gmail.com"},{"courses":["Law"],"email":"Cynthia.Rogers@gmail.com"},{"courses":["Sculpture"],"email":"Hannah.Rogers@gmail.com"},{"courses":["Management"],"email":"Janet.Rogers@gmail.com"},{"courses":["Sculpture"],"email":"Johnny.Rogers@gmail.com"},{"courses":["Management"],"email":"Joyce.Rogers@gmail.com"},{"courses":["Law"],"email":"Patricia.Rogers@gmail.com"},{"courses":["Accounting"],"email":"Victoria.Rogers@gmail.com"},{"courses":["Biology"],"email":"Wayne.Rogers@gmail.com"},{"courses":["English"],"email":"Amber.Ross@gmail.com"},{"courses":["Chemistry"],"email":"Jesse.Ross@gmail.com"},{"courses":["Chemistry"],"email":"Keith.Ross@gmail.com"},{"courses":["Biology"],"email":"Lawrence.Ross@gmail.com"},{"courses":["Mathematics"],"email":"Olivia.Ross@gmail.com"},{"courses":["Latin"],"email":"Christina.Ruiz@gmail.com"},{"courses":["English"],"email":"Jessica.Ruiz@gmail.com"},{"courses":["Biology"],"email":"Jonathan.Ruiz@gmail.com"},{"courses":["Literature and Poetry"],"email":"Larry.Ruiz@gmail.com"},{"courses":["Sculpture"],"email":"Sandra.Ruiz@gmail.com"},{"courses":["History"],"email":"David.Sanchez@gmail.com"},{"courses":["Management"],"email":"Edward.Sanchez@gmail.com"},{"courses":["Drawing"],"email":"Eric.Sanchez@gmail.com"},{"courses":["Physics"],"email":"Martha.Sanchez@gmail.com"},{"courses":["Law"],"email":"Michelle.Sanchez@gmail.com"},{"courses":["Accounting"],"email":"Peter.Sanchez@gmail.com"},{"courses":["Mathematics"],"email":"Sarah.Sanchez@gmail.com"},{"courses":["Literature and Poetry"],"email":"William.Sanchez@gmail.com"},{"courses":["Accounting"],"email":"Zachary.Sanchez@gmail.com"},{"courses":["Accounting"],"email":"Brian.Sanders@gmail.com"},{"courses":["English"],"email":"Christopher.Sanders@gmail.com"},{"courses":["English"],"email":"Dennis.Sanders@gmail.com"},{"courses":["Mathematics"],"email":"Katherine.Sanders@gmail.com"},{"courses":["History"],"email":"William.Sanders@gmail.com"},{"courses":["English"],"email":"Dorothy.Scott@gmail.com"},{"courses":["Latin"],"email":"James.Scott@gmail.com"},{"courses":["Sculpture"],"email":"Jeremy.Scott@gmail.com"},{"courses":["Accounting"],"email":"Jordan.Scott@gmail.com"},{"courses":["Mathematics"],"email":"Lauren.Scott@gmail.com"},{"courses":["Physics"],"email":"Sophia.Scott@gmail.com"},{"courses":["Mathematics"],"email":"Andrew.Smith@gmail.com"},{"courses":["Management"],"email":"Evelyn.Smith@gmail.com"},{"courses":["Drawing"],"email":"Maria.Smith@gmail.com"},{"courses":["Literature and Poetry"],"email":"Rachel.Smith@gmail.com"},{"courses":["Latin"],"email":"Andrea.Stewart@gmail.com"},{"courses":["Drawing"],"email":"Brian.Stewart@gmail.com"},{"courses":["Sculpture"],"email":"Debra.Stewart@gmail.com"},{"courses":["History"],"email":"Frances.Stewart@gmail.com"},{"courses":["Literature and Poetry"],"email":"Helen.Stewart@gmail.com"},{"courses":["Drawing"],"email":"Andrea.Taylor@gmail.com"},{"courses":["Sculpture"],"email":"George.Taylor@gmail.com"},{"courses":["History"],"email":"Beverly.Thomas@gmail.com"},{"courses":["Management"],"email":"Carl.Thomas@gmail.com"},{"courses":["Law"],"email":"Heather.Thomas@gmail.com"},{"courses":["Accounting"],"email":"Jerry.Thomas@gmail.com"},{"courses":["English"],"email":"Lawrence.Thomas@gmail.com"},{"courses":["Law"],"email":"Ruth.Thomas@gmail.com"},{"courses":["Biology"],"email":"Ryan.Thomas@gmail.com"},{"courses":["Physics"],"email":"Anthony.Thompson@gmail.com"},{"courses":["Law","English"],"email":"Ethan.Thompson@gmail.com"},{"courses":["Drawing"],"email":"Jacqueline.Thompson@gmail.com"},{"courses":["Biology"],"email":"Angela.Torres@gmail.com"},{"courses":["Literature and Poetry"],"email":"Carol.Torres@gmail.com"},{"courses":["Sculpture"],"email":"Cynthia.Torres@gmail.com"},{"courses":["Management"],"email":"Emma.Torres@gmail.com"},{"courses":["Sculpture"],"email":"Grace.Torres@gmail.com"},{"courses":["Mathematics"],"email":"Jacob.Torres@gmail.com"},{"courses":["Chemistry"],"email":"Logan.Torres@gmail.com"},{"courses":["Latin"],"email":"Natalie.Torres@gmail.com"},{"courses":["Accounting"],"email":"Susan.Torres@gmail.com"},{"courses":["English"],"email":"Donald.Turner@gmail.com"},{"courses":["Management"],"email":"Hannah.Turner@gmail.com"},{"courses":["Latin"],"email":"Helen.Turner@gmail.com"},{"courses":["Mathematics"],"email":"Sarah.Turner@gmail.com"},{"courses":["Sculpture"],"email":"Aaron.Walker@gmail.com"},{"courses":["English"],"email":"Adam.Walker@gmail.com"},{"courses":["Law"],"email":"Betty.Walker@gmail.com"},{"courses":["Chemistry"],"email":"Patricia.Walker@gmail.com"},{"courses":["History"],"email":"Sophia.Walker@gmail.com"},{"courses":["Sculpture"],"email":"Amber.Ward@gmail.com"},{"courses":["English"],"email":"Dorothy.Ward@gmail.com"},{"courses":["Law"],"email":"Joseph.Ward@gmail.com"},{"courses":["Physics"],"email":"Joshua.Ward@gmail.com"},{"courses":["Management"],"email":"Thomas.Ward@gmail.com"},{"courses":["History"],"email":"Andrea.Watson@gmail.com"},{"courses":["Physics"],"email":"Beverly.Watson@gmail.com"},{"courses":["Management"],"email":"Carl.Watson@gmail.com"},{"courses":["Drawing"],"email":"Gerald.Watson@gmail.com"},{"courses":["English"],"email":"Joan.Watson@gmail.com"},{"courses":["Latin"],"email":"Mark.Watson@gmail.com"},{"courses":["Drawing"],"email":"Philip.Watson@gmail.com"},{"courses":["Literature and Poetry"],"email":"Henry.White@gmail.com"},{"courses":["History"],"email":"Jack.White@gmail.com"},{"courses":["Biology"],"email":"Roger.White@gmail.com"},{"courses":["History"],"email":"Scott.White@gmail.com"},{"courses":["Latin"],"email":"Cynthia.Williams@gmail.com"},{"courses":["Law"],"email":"Margaret.Williams@gmail.com"},{"courses":["Physics"],"email":"Nicholas.Williams@gmail.com"},{"courses":["History","Law"],"email":"Terry.Williams@gmail.com"},{"courses":["History"],"email":"Walter.Williams@gmail.com"},{"courses":["Latin"],"email":"Barbara.Wilson@gmail.com"},{"courses":["Sculpture"],"email":"Jacqueline.Wilson@gmail.com"},{"courses":["Physics"],"email":"Sara.Wilson@gmail.com"},{"courses":["Mathematics"],"email":"Brandon.Wood@gmail.com"},{"courses":["English"],"email":"Gary.Wood@gmail.com"},{"courses":["Latin"],"email":"Nicholas.Wood@gmail.com"},{"courses":["Chemistry"],"email":"Ruth.Wood@gmail.com"},{"courses":["Management"],"email":"Brian.Wright@gmail.com"},{"courses":["Mathematics"],"email":"Carl.Wright@gmail.com"},{"courses":["Drawing"],"email":"Eugene.Wright@gmail.com"},{"courses":["Accounting","Sculpture"],"email":"Juan.Wright@gmail.com"},{"courses":["Law"],"email":"Maria.Wright@gmail.com"},{"courses":["Latin"],"email":"Marie.Wright@gmail.com"},{"courses":["Drawing"],"email":"Aaron.Young@gmail.com"},{"courses":["English"],"email":"Beverly.Young@gmail.com"},{"courses":["Management"],"email":"Brandon.Young@gmail.com"},{"courses":["Mathematics"],"email":"Christina.Young@gmail.com"},{"courses":["Accounting"],"email":"Grace.Young@gmail.com"},{"courses":["Literature and Poetry"],"email":"Helen.Young@gmail.com"},{"courses":["Biology"],"email":"Sarah.Young@gmail.com"}]